mixpanel_utils/__init__.py
mixpanel_utils/paginator.py
mixpanel_utils-2.2.7.dist-info/licenses/LICENSE
mixpanel_utils-2.2.7.dist-info/METADATA
mixpanel_utils-2.2.7.dist-info/WHEEL
mixpanel_utils-2.2.7.dist-info/top_level.txt
mixpanel_utils-2.2.7.dist-info/RECORD
