Metadata-Version: 2.4
Name: mixpanel-utils
Version: 2.2.7
Summary: Utilities-only module for exporting and importing data into Mixpanel. NOT for server-side app tracking.
Home-page: https://github.com/mixpanel/mixpanel-utils
Author: Jared McFarland
Author-email: jared@mixpanel.com
Requires-Python: >=3
License-File: LICENSE
Dynamic: author
Dynamic: author-email
Dynamic: description
Dynamic: home-page
Dynamic: license-file
Dynamic: requires-python
Dynamic: summary
